vishwakarma/__init__.py
vishwakarma/pdfplot.py
vishwakarma/pgmplot.py
vishwakarma/pmfplot.py
vishwakarma-0.1.1.dist-info/LICENSE
vishwakarma-0.1.1.dist-info/WHEEL
vishwakarma-0.1.1.dist-info/METADATA
vishwakarma-0.1.1.dist-info/RECORD
