Metadata-Version: 2.1
Name: vishwakarma
Version: 0.1.1
Summary: Python visualization library for Probabilistic Graphical Models, Discrete & Continuous Distributions, and a lot more!
Home-page: https://github.com/diagram-ai/vishwakarma
License: UNKNOWN
Author: Diagram AI
Author-email: notes@diagram.ai
Classifier: License :: OSI Approved :: MIT License
Classifier: Operating System :: OS Independent
Classifier: Programming Language :: Python :: 3
